msg.py
avilabsutils_msg-0.0.1.dist-info/METADATA
avilabsutils_msg-0.0.1.dist-info/WHEEL
avilabsutils_msg-0.0.1.dist-info/top_level.txt
avilabsutils_msg-0.0.1.dist-info/RECORD
