Metadata-Version: 2.1
Name: avilabsutils-msg
Version: 0.0.1
Summary: Functions to send messages.
Home-page: https://github.com/avilay/utils/msg
Author: Avilay Parekh
Author-email: avilay@gmail.com
License: UNKNOWN
Platform: UNKNOWN
Classifier: Programming Language :: Python :: 3
Classifier: License :: OSI Approved :: MIT License
Classifier: Operating System :: OS Independent
Requires-Python: >=3.6
Requires-Dist: twilio
Requires-Dist: avilabsutils-cprint
